Faizan_two_machines
