Metadata-Version: 2.1
Name: Faizan-two-machines
Version: 0.4
Summary: This Johnson Scheduling Algorithm works on Data Frames
Home-page: https://github.com/Faizan272/Faizan_two_machines
Download-URL: https://github.com/Faizan272/Faizan_two_machines/archive/refs/tags/0.4.tar.gz
Author: FAIZAN SIDDIQI
Author-email: faizansiddiqi27@gmail.com
License: MIT
License-File: LICENSE.txt
